MANIFEST.in
README.rst
setup.py
bin/cpfile
cpfile/__init__.py
cpfile/cpfile.py
cpfile.egg-info/PKG-INFO
cpfile.egg-info/SOURCES.txt
cpfile.egg-info/dependency_links.txt
cpfile.egg-info/not-zip-safe
cpfile.egg-info/top_level.txt