Metadata-Version: 1.1
Name: cpfile
Version: 1.0.3.1
Summary: A python module ment to make working with files much easier
Home-page: encry.cpnerd.koding.io/cpfile.py
Author: CPNerd
Author-email: shadow889566@gmail.com
License: MIT
Platform: UNKNOWN
Classifier: Development Status :: 5 - Production/Stable
Classifier: Intended Audience :: Developers
